josephliu164_tools/__init__.py
josephliu164_tools/__pycache__/__init__.cpython-310.pyc
josephliu164_tools/tools/__init__.py
josephliu164_tools/tools/hello_world_tool.py
josephliu164_tools/tools/utils.py
josephliu164_tools/tools/__pycache__/__init__.cpython-310.pyc
josephliu164_tools/tools/__pycache__/utils.cpython-310.pyc
josephliu164_tools/yamls/hello_world_tool.yaml
josephliu164_tools/yamls/store_message_to_redis.yaml
tests/__init__.py
tests/detailed_test.py
tests/force_output_test.py
tests/test_hello_world_tool.py
tests/test_package.py
tests/test_utils.py
tests/test_yaml.py
josephliu164_tools-0.1.2.dist-info/METADATA
josephliu164_tools-0.1.2.dist-info/WHEEL
josephliu164_tools-0.1.2.dist-info/entry_points.txt
josephliu164_tools-0.1.2.dist-info/top_level.txt
josephliu164_tools-0.1.2.dist-info/RECORD
