Metadata-Version: 2.1
Name: josephliu164_tools
Version: 0.1.2
Requires-Dist: redis
Requires-Dist: supabase
Requires-Dist: promptflow
Requires-Dist: asyncio
Requires-Dist: pyyaml
